[
  {
    "name": "block.0.attn.out.weight",
    "int4_bin": "/home/ricky/Desktop/Clocher/quant/q4_parts/block.0.attn.out.weight.int4",
    "scale_bin": "/home/ricky/Desktop/Clocher/quant/q4_parts/block.0.attn.out.weight.scale.fp16",
    "per": "row",
    "rows": 2880,
    "cols": 4096,
    "scale_dtype": "fp16",
    "pack": "nibble_lohi",
    "zp": 0,
    "symmetric": true
  },
  {
    "name": "block.0.attn.qkv.weight",
    "int4_bin": "/home/ricky/Desktop/Clocher/quant/q4_parts/block.0.attn.qkv.weight.int4",
    "scale_bin": "/home/ricky/Desktop/Clocher/quant/q4_parts/block.0.attn.qkv.weight.scale.fp16",
    "per": "row",
    "rows": 5120,
    "cols": 2880,
    "scale_dtype": "fp16",
    "pack": "nibble_lohi",
    "zp": 0,
    "symmetric": true
  },
  {
    "name": "block.0.mlp.gate.weight",
    "int4_bin": "/home/ricky/Desktop/Clocher/quant/q4_parts/block.0.mlp.gate.weight.int4",
    "scale_bin": "/home/ricky/Desktop/Clocher/quant/q4_parts/block.0.mlp.gate.weight.scale.fp16",
    "per": "row",
    "rows": 32,
    "cols": 2880,
    "scale_dtype": "fp16",
    "pack": "nibble_lohi",
    "zp": 0,
    "symmetric": true
  },
  {
    "name": "block.1.attn.out.weight",
    "int4_bin": "/home/ricky/Desktop/Clocher/quant/q4_parts/block.1.attn.out.weight.int4",
    "scale_bin": "/home/ricky/Desktop/Clocher/quant/q4_parts/block.1.attn.out.weight.scale.fp16",
    "per": "row",
    "rows": 2880,
    "cols": 4096,
    "scale_dtype": "fp16",
    "pack": "nibble_lohi",
    "zp": 0,
    "symmetric": true
  },
  {
    "name": "block.1.attn.qkv.weight",
    "int4_bin": "/home/ricky/Desktop/Clocher/quant/q4_parts/block.1.attn.qkv.weight.int4",
    "scale_bin": "/home/ricky/Desktop/Clocher/quant/q4_parts/block.1.attn.qkv.weight.scale.fp16",
    "per": "row",
    "rows": 5120,
    "cols": 2880,
    "scale_dtype": "fp16",
    "pack": "nibble_lohi",
    "zp": 0,
    "symmetric": true
  },
  {
    "name": "block.1.mlp.gate.weight",
    "int4_bin": "/home/ricky/Desktop/Clocher/quant/q4_parts/block.1.mlp.gate.weight.int4",
    "scale_bin": "/home/ricky/Desktop/Clocher/quant/q4_parts/block.1.mlp.gate.weight.scale.fp16",
    "per": "row",
    "rows": 32,
    "cols": 2880,
    "scale_dtype": "fp16",
    "pack": "nibble_lohi",
    "zp": 0,
    "symmetric": true
  },
  {
    "name": "block.10.attn.out.weight",
    "int4_bin": "/home/ricky/Desktop/Clocher/quant/q4_parts/block.10.attn.out.weight.int4",
    "scale_bin": "/home/ricky/Desktop/Clocher/quant/q4_parts/block.10.attn.out.weight.scale.fp16",
    "per": "row",
    "rows": 2880,
    "cols": 4096,
    "scale_dtype": "fp16",
    "pack": "nibble_lohi",
    "zp": 0,
    "symmetric": true
  },
  {
    "name": "block.10.attn.qkv.weight",
    "int4_bin": "/home/ricky/Desktop/Clocher/quant/q4_parts/block.10.attn.qkv.weight.int4",
    "scale_bin": "/home/ricky/Desktop/Clocher/quant/q4_parts/block.10.attn.qkv.weight.scale.fp16",
    "per": "row",
    "rows": 5120,
    "cols": 2880,
    "scale_dtype": "fp16",
    "pack": "nibble_lohi",
    "zp": 0,
    "symmetric": true
  },
  {
    "name": "block.10.mlp.gate.weight",
    "int4_bin": "/home/ricky/Desktop/Clocher/quant/q4_parts/block.10.mlp.gate.weight.int4",
    "scale_bin": "/home/ricky/Desktop/Clocher/quant/q4_parts/block.10.mlp.gate.weight.scale.fp16",
    "per": "row",
    "rows": 32,
    "cols": 2880,
    "scale_dtype": "fp16",
    "pack": "nibble_lohi",
    "zp": 0,
    "symmetric": true
  },
  {
    "name": "block.11.attn.out.weight",
    "int4_bin": "/home/ricky/Desktop/Clocher/quant/q4_parts/block.11.attn.out.weight.int4",
    "scale_bin": "/home/ricky/Desktop/Clocher/quant/q4_parts/block.11.attn.out.weight.scale.fp16",
    "per": "row",
    "rows": 2880,
    "cols": 4096,
    "scale_dtype": "fp16",
    "pack": "nibble_lohi",
    "zp": 0,
    "symmetric": true
  },
  {
    "name": "block.11.attn.qkv.weight",
    "int4_bin": "/home/ricky/Desktop/Clocher/quant/q4_parts/block.11.attn.qkv.weight.int4",
    "scale_bin": "/home/ricky/Desktop/Clocher/quant/q4_parts/block.11.attn.qkv.weight.scale.fp16",
    "per": "row",
    "rows": 5120,
    "cols": 2880,
    "scale_dtype": "fp16",
    "pack": "nibble_lohi",
    "zp": 0,
    "symmetric": true
  },
  {
    "name": "block.11.mlp.gate.weight",
    "int4_bin": "/home/ricky/Desktop/Clocher/quant/q4_parts/block.11.mlp.gate.weight.int4",
    "scale_bin": "/home/ricky/Desktop/Clocher/quant/q4_parts/block.11.mlp.gate.weight.scale.fp16",
    "per": "row",
    "rows": 32,
    "cols": 2880,
    "scale_dtype": "fp16",
    "pack": "nibble_lohi",
    "zp": 0,
    "symmetric": true
  },
  {
    "name": "block.12.attn.out.weight",
    "int4_bin": "/home/ricky/Desktop/Clocher/quant/q4_parts/block.12.attn.out.weight.int4",
    "scale_bin": "/home/ricky/Desktop/Clocher/quant/q4_parts/block.12.attn.out.weight.scale.fp16",
    "per": "row",
    "rows": 2880,
    "cols": 4096,
    "scale_dtype": "fp16",
    "pack": "nibble_lohi",
    "zp": 0,
    "symmetric": true
  },
  {
    "name": "block.12.attn.qkv.weight",
    "int4_bin": "/home/ricky/Desktop/Clocher/quant/q4_parts/block.12.attn.qkv.weight.int4",
    "scale_bin": "/home/ricky/Desktop/Clocher/quant/q4_parts/block.12.attn.qkv.weight.scale.fp16",
    "per": "row",
    "rows": 5120,
    "cols": 2880,
    "scale_dtype": "fp16",
    "pack": "nibble_lohi",
    "zp": 0,
    "symmetric": true
  },
  {
    "name": "block.12.mlp.gate.weight",
    "int4_bin": "/home/ricky/Desktop/Clocher/quant/q4_parts/block.12.mlp.gate.weight.int4",
    "scale_bin": "/home/ricky/Desktop/Clocher/quant/q4_parts/block.12.mlp.gate.weight.scale.fp16",
    "per": "row",
    "rows": 32,
    "cols": 2880,
    "scale_dtype": "fp16",
    "pack": "nibble_lohi",
    "zp": 0,
    "symmetric": true
  },
  {
    "name": "block.13.attn.out.weight",
    "int4_bin": "/home/ricky/Desktop/Clocher/quant/q4_parts/block.13.attn.out.weight.int4",
    "scale_bin": "/home/ricky/Desktop/Clocher/quant/q4_parts/block.13.attn.out.weight.scale.fp16",
    "per": "row",
    "rows": 2880,
    "cols": 4096,
    "scale_dtype": "fp16",
    "pack": "nibble_lohi",
    "zp": 0,
    "symmetric": true
  },
  {
    "name": "block.13.attn.qkv.weight",
    "int4_bin": "/home/ricky/Desktop/Clocher/quant/q4_parts/block.13.attn.qkv.weight.int4",
    "scale_bin": "/home/ricky/Desktop/Clocher/quant/q4_parts/block.13.attn.qkv.weight.scale.fp16",
    "per": "row",
    "rows": 5120,
    "cols": 2880,
    "scale_dtype": "fp16",
    "pack": "nibble_lohi",
    "zp": 0,
    "symmetric": true
  },
  {
    "name": "block.13.mlp.gate.weight",
    "int4_bin": "/home/ricky/Desktop/Clocher/quant/q4_parts/block.13.mlp.gate.weight.int4",
    "scale_bin": "/home/ricky/Desktop/Clocher/quant/q4_parts/block.13.mlp.gate.weight.scale.fp16",
    "per": "row",
    "rows": 32,
    "cols": 2880,
    "scale_dtype": "fp16",
    "pack": "nibble_lohi",
    "zp": 0,
    "symmetric": true
  },
  {
    "name": "block.14.attn.out.weight",
    "int4_bin": "/home/ricky/Desktop/Clocher/quant/q4_parts/block.14.attn.out.weight.int4",
    "scale_bin": "/home/ricky/Desktop/Clocher/quant/q4_parts/block.14.attn.out.weight.scale.fp16",
    "per": "row",
    "rows": 2880,
    "cols": 4096,
    "scale_dtype": "fp16",
    "pack": "nibble_lohi",
    "zp": 0,
    "symmetric": true
  },
  {
    "name": "block.14.attn.qkv.weight",
    "int4_bin": "/home/ricky/Desktop/Clocher/quant/q4_parts/block.14.attn.qkv.weight.int4",
    "scale_bin": "/home/ricky/Desktop/Clocher/quant/q4_parts/block.14.attn.qkv.weight.scale.fp16",
    "per": "row",
    "rows": 5120,
    "cols": 2880,
    "scale_dtype": "fp16",
    "pack": "nibble_lohi",
    "zp": 0,
    "symmetric": true
  },
  {
    "name": "block.14.mlp.gate.weight",
    "int4_bin": "/home/ricky/Desktop/Clocher/quant/q4_parts/block.14.mlp.gate.weight.int4",
    "scale_bin": "/home/ricky/Desktop/Clocher/quant/q4_parts/block.14.mlp.gate.weight.scale.fp16",
    "per": "row",
    "rows": 32,
    "cols": 2880,
    "scale_dtype": "fp16",
    "pack": "nibble_lohi",
    "zp": 0,
    "symmetric": true
  },
  {
    "name": "block.15.attn.out.weight",
    "int4_bin": "/home/ricky/Desktop/Clocher/quant/q4_parts/block.15.attn.out.weight.int4",
    "scale_bin": "/home/ricky/Desktop/Clocher/quant/q4_parts/block.15.attn.out.weight.scale.fp16",
    "per": "row",
    "rows": 2880,
    "cols": 4096,
    "scale_dtype": "fp16",
    "pack": "nibble_lohi",
    "zp": 0,
    "symmetric": true
  },
  {
    "name": "block.15.attn.qkv.weight",
    "int4_bin": "/home/ricky/Desktop/Clocher/quant/q4_parts/block.15.attn.qkv.weight.int4",
    "scale_bin": "/home/ricky/Desktop/Clocher/quant/q4_parts/block.15.attn.qkv.weight.scale.fp16",
    "per": "row",
    "rows": 5120,
    "cols": 2880,
    "scale_dtype": "fp16",
    "pack": "nibble_lohi",
    "zp": 0,
    "symmetric": true
  },
  {
    "name": "block.15.mlp.gate.weight",
    "int4_bin": "/home/ricky/Desktop/Clocher/quant/q4_parts/block.15.mlp.gate.weight.int4",
    "scale_bin": "/home/ricky/Desktop/Clocher/quant/q4_parts/block.15.mlp.gate.weight.scale.fp16",
    "per": "row",
    "rows": 32,
    "cols": 2880,
    "scale_dtype": "fp16",
    "pack": "nibble_lohi",
    "zp": 0,
    "symmetric": true
  },
  {
    "name": "block.16.attn.out.weight",
    "int4_bin": "/home/ricky/Desktop/Clocher/quant/q4_parts/block.16.attn.out.weight.int4",
    "scale_bin": "/home/ricky/Desktop/Clocher/quant/q4_parts/block.16.attn.out.weight.scale.fp16",
    "per": "row",
    "rows": 2880,
    "cols": 4096,
    "scale_dtype": "fp16",
    "pack": "nibble_lohi",
    "zp": 0,
    "symmetric": true
  },
  {
    "name": "block.16.attn.qkv.weight",
    "int4_bin": "/home/ricky/Desktop/Clocher/quant/q4_parts/block.16.attn.qkv.weight.int4",
    "scale_bin": "/home/ricky/Desktop/Clocher/quant/q4_parts/block.16.attn.qkv.weight.scale.fp16",
    "per": "row",
    "rows": 5120,
    "cols": 2880,
    "scale_dtype": "fp16",
    "pack": "nibble_lohi",
    "zp": 0,
    "symmetric": true
  },
  {
    "name": "block.16.mlp.gate.weight",
    "int4_bin": "/home/ricky/Desktop/Clocher/quant/q4_parts/block.16.mlp.gate.weight.int4",
    "scale_bin": "/home/ricky/Desktop/Clocher/quant/q4_parts/block.16.mlp.gate.weight.scale.fp16",
    "per": "row",
    "rows": 32,
    "cols": 2880,
    "scale_dtype": "fp16",
    "pack": "nibble_lohi",
    "zp": 0,
    "symmetric": true
  },
  {
    "name": "block.17.attn.out.weight",
    "int4_bin": "/home/ricky/Desktop/Clocher/quant/q4_parts/block.17.attn.out.weight.int4",
    "scale_bin": "/home/ricky/Desktop/Clocher/quant/q4_parts/block.17.attn.out.weight.scale.fp16",
    "per": "row",
    "rows": 2880,
    "cols": 4096,
    "scale_dtype": "fp16",
    "pack": "nibble_lohi",
    "zp": 0,
    "symmetric": true
  },
  {
    "name": "block.17.attn.qkv.weight",
    "int4_bin": "/home/ricky/Desktop/Clocher/quant/q4_parts/block.17.attn.qkv.weight.int4",
    "scale_bin": "/home/ricky/Desktop/Clocher/quant/q4_parts/block.17.attn.qkv.weight.scale.fp16",
    "per": "row",
    "rows": 5120,
    "cols": 2880,
    "scale_dtype": "fp16",
    "pack": "nibble_lohi",
    "zp": 0,
    "symmetric": true
  },
  {
    "name": "block.17.mlp.gate.weight",
    "int4_bin": "/home/ricky/Desktop/Clocher/quant/q4_parts/block.17.mlp.gate.weight.int4",
    "scale_bin": "/home/ricky/Desktop/Clocher/quant/q4_parts/block.17.mlp.gate.weight.scale.fp16",
    "per": "row",
    "rows": 32,
    "cols": 2880,
    "scale_dtype": "fp16",
    "pack": "nibble_lohi",
    "zp": 0,
    "symmetric": true
  },
  {
    "name": "block.18.attn.out.weight",
    "int4_bin": "/home/ricky/Desktop/Clocher/quant/q4_parts/block.18.attn.out.weight.int4",
    "scale_bin": "/home/ricky/Desktop/Clocher/quant/q4_parts/block.18.attn.out.weight.scale.fp16",
    "per": "row",
    "rows": 2880,
    "cols": 4096,
    "scale_dtype": "fp16",
    "pack": "nibble_lohi",
    "zp": 0,
    "symmetric": true
  },
  {
    "name": "block.18.attn.qkv.weight",
    "int4_bin": "/home/ricky/Desktop/Clocher/quant/q4_parts/block.18.attn.qkv.weight.int4",
    "scale_bin": "/home/ricky/Desktop/Clocher/quant/q4_parts/block.18.attn.qkv.weight.scale.fp16",
    "per": "row",
    "rows": 5120,
    "cols": 2880,
    "scale_dtype": "fp16",
    "pack": "nibble_lohi",
    "zp": 0,
    "symmetric": true
  },
  {
    "name": "block.18.mlp.gate.weight",
    "int4_bin": "/home/ricky/Desktop/Clocher/quant/q4_parts/block.18.mlp.gate.weight.int4",
    "scale_bin": "/home/ricky/Desktop/Clocher/quant/q4_parts/block.18.mlp.gate.weight.scale.fp16",
    "per": "row",
    "rows": 32,
    "cols": 2880,
    "scale_dtype": "fp16",
    "pack": "nibble_lohi",
    "zp": 0,
    "symmetric": true
  },
  {
    "name": "block.19.attn.out.weight",
    "int4_bin": "/home/ricky/Desktop/Clocher/quant/q4_parts/block.19.attn.out.weight.int4",
    "scale_bin": "/home/ricky/Desktop/Clocher/quant/q4_parts/block.19.attn.out.weight.scale.fp16",
    "per": "row",
    "rows": 2880,
    "cols": 4096,
    "scale_dtype": "fp16",
    "pack": "nibble_lohi",
    "zp": 0,
    "symmetric": true
  },
  {
    "name": "block.19.attn.qkv.weight",
    "int4_bin": "/home/ricky/Desktop/Clocher/quant/q4_parts/block.19.attn.qkv.weight.int4",
    "scale_bin": "/home/ricky/Desktop/Clocher/quant/q4_parts/block.19.attn.qkv.weight.scale.fp16",
    "per": "row",
    "rows": 5120,
    "cols": 2880,
    "scale_dtype": "fp16",
    "pack": "nibble_lohi",
    "zp": 0,
    "symmetric": true
  },
  {
    "name": "block.19.mlp.gate.weight",
    "int4_bin": "/home/ricky/Desktop/Clocher/quant/q4_parts/block.19.mlp.gate.weight.int4",
    "scale_bin": "/home/ricky/Desktop/Clocher/quant/q4_parts/block.19.mlp.gate.weight.scale.fp16",
    "per": "row",
    "rows": 32,
    "cols": 2880,
    "scale_dtype": "fp16",
    "pack": "nibble_lohi",
    "zp": 0,
    "symmetric": true
  },
  {
    "name": "block.2.attn.out.weight",
    "int4_bin": "/home/ricky/Desktop/Clocher/quant/q4_parts/block.2.attn.out.weight.int4",
    "scale_bin": "/home/ricky/Desktop/Clocher/quant/q4_parts/block.2.attn.out.weight.scale.fp16",
    "per": "row",
    "rows": 2880,
    "cols": 4096,
    "scale_dtype": "fp16",
    "pack": "nibble_lohi",
    "zp": 0,
    "symmetric": true
  },
  {
    "name": "block.2.attn.qkv.weight",
    "int4_bin": "/home/ricky/Desktop/Clocher/quant/q4_parts/block.2.attn.qkv.weight.int4",
    "scale_bin": "/home/ricky/Desktop/Clocher/quant/q4_parts/block.2.attn.qkv.weight.scale.fp16",
    "per": "row",
    "rows": 5120,
    "cols": 2880,
    "scale_dtype": "fp16",
    "pack": "nibble_lohi",
    "zp": 0,
    "symmetric": true
  },
  {
    "name": "block.2.mlp.gate.weight",
    "int4_bin": "/home/ricky/Desktop/Clocher/quant/q4_parts/block.2.mlp.gate.weight.int4",
    "scale_bin": "/home/ricky/Desktop/Clocher/quant/q4_parts/block.2.mlp.gate.weight.scale.fp16",
    "per": "row",
    "rows": 32,
    "cols": 2880,
    "scale_dtype": "fp16",
    "pack": "nibble_lohi",
    "zp": 0,
    "symmetric": true
  },
  {
    "name": "block.20.attn.out.weight",
    "int4_bin": "/home/ricky/Desktop/Clocher/quant/q4_parts/block.20.attn.out.weight.int4",
    "scale_bin": "/home/ricky/Desktop/Clocher/quant/q4_parts/block.20.attn.out.weight.scale.fp16",
    "per": "row",
    "rows": 2880,
    "cols": 4096,
    "scale_dtype": "fp16",
    "pack": "nibble_lohi",
    "zp": 0,
    "symmetric": true
  },
  {
    "name": "block.20.attn.qkv.weight",
    "int4_bin": "/home/ricky/Desktop/Clocher/quant/q4_parts/block.20.attn.qkv.weight.int4",
    "scale_bin": "/home/ricky/Desktop/Clocher/quant/q4_parts/block.20.attn.qkv.weight.scale.fp16",
    "per": "row",
    "rows": 5120,
    "cols": 2880,
    "scale_dtype": "fp16",
    "pack": "nibble_lohi",
    "zp": 0,
    "symmetric": true
  },
  {
    "name": "block.20.mlp.gate.weight",
    "int4_bin": "/home/ricky/Desktop/Clocher/quant/q4_parts/block.20.mlp.gate.weight.int4",
    "scale_bin": "/home/ricky/Desktop/Clocher/quant/q4_parts/block.20.mlp.gate.weight.scale.fp16",
    "per": "row",
    "rows": 32,
    "cols": 2880,
    "scale_dtype": "fp16",
    "pack": "nibble_lohi",
    "zp": 0,
    "symmetric": true
  },
  {
    "name": "block.21.attn.out.weight",
    "int4_bin": "/home/ricky/Desktop/Clocher/quant/q4_parts/block.21.attn.out.weight.int4",
    "scale_bin": "/home/ricky/Desktop/Clocher/quant/q4_parts/block.21.attn.out.weight.scale.fp16",
    "per": "row",
    "rows": 2880,
    "cols": 4096,
    "scale_dtype": "fp16",
    "pack": "nibble_lohi",
    "zp": 0,
    "symmetric": true
  },
  {
    "name": "block.21.attn.qkv.weight",
    "int4_bin": "/home/ricky/Desktop/Clocher/quant/q4_parts/block.21.attn.qkv.weight.int4",
    "scale_bin": "/home/ricky/Desktop/Clocher/quant/q4_parts/block.21.attn.qkv.weight.scale.fp16",
    "per": "row",
    "rows": 5120,
    "cols": 2880,
    "scale_dtype": "fp16",
    "pack": "nibble_lohi",
    "zp": 0,
    "symmetric": true
  },
  {
    "name": "block.21.mlp.gate.weight",
    "int4_bin": "/home/ricky/Desktop/Clocher/quant/q4_parts/block.21.mlp.gate.weight.int4",
    "scale_bin": "/home/ricky/Desktop/Clocher/quant/q4_parts/block.21.mlp.gate.weight.scale.fp16",
    "per": "row",
    "rows": 32,
    "cols": 2880,
    "scale_dtype": "fp16",
    "pack": "nibble_lohi",
    "zp": 0,
    "symmetric": true
  },
  {
    "name": "block.22.attn.out.weight",
    "int4_bin": "/home/ricky/Desktop/Clocher/quant/q4_parts/block.22.attn.out.weight.int4",
    "scale_bin": "/home/ricky/Desktop/Clocher/quant/q4_parts/block.22.attn.out.weight.scale.fp16",
    "per": "row",
    "rows": 2880,
    "cols": 4096,
    "scale_dtype": "fp16",
    "pack": "nibble_lohi",
    "zp": 0,
    "symmetric": true
  },
  {
    "name": "block.22.attn.qkv.weight",
    "int4_bin": "/home/ricky/Desktop/Clocher/quant/q4_parts/block.22.attn.qkv.weight.int4",
    "scale_bin": "/home/ricky/Desktop/Clocher/quant/q4_parts/block.22.attn.qkv.weight.scale.fp16",
    "per": "row",
    "rows": 5120,
    "cols": 2880,
    "scale_dtype": "fp16",
    "pack": "nibble_lohi",
    "zp": 0,
    "symmetric": true
  },
  {
    "name": "block.22.mlp.gate.weight",
    "int4_bin": "/home/ricky/Desktop/Clocher/quant/q4_parts/block.22.mlp.gate.weight.int4",
    "scale_bin": "/home/ricky/Desktop/Clocher/quant/q4_parts/block.22.mlp.gate.weight.scale.fp16",
    "per": "row",
    "rows": 32,
    "cols": 2880,
    "scale_dtype": "fp16",
    "pack": "nibble_lohi",
    "zp": 0,
    "symmetric": true
  },
  {
    "name": "block.23.attn.out.weight",
    "int4_bin": "/home/ricky/Desktop/Clocher/quant/q4_parts/block.23.attn.out.weight.int4",
    "scale_bin": "/home/ricky/Desktop/Clocher/quant/q4_parts/block.23.attn.out.weight.scale.fp16",
    "per": "row",
    "rows": 2880,
    "cols": 4096,
    "scale_dtype": "fp16",
    "pack": "nibble_lohi",
    "zp": 0,
    "symmetric": true
  },
  {
    "name": "block.23.attn.qkv.weight",
    "int4_bin": "/home/ricky/Desktop/Clocher/quant/q4_parts/block.23.attn.qkv.weight.int4",
    "scale_bin": "/home/ricky/Desktop/Clocher/quant/q4_parts/block.23.attn.qkv.weight.scale.fp16",
    "per": "row",
    "rows": 5120,
    "cols": 2880,
    "scale_dtype": "fp16",
    "pack": "nibble_lohi",
    "zp": 0,
    "symmetric": true
  },
  {
    "name": "block.23.mlp.gate.weight",
    "int4_bin": "/home/ricky/Desktop/Clocher/quant/q4_parts/block.23.mlp.gate.weight.int4",
    "scale_bin": "/home/ricky/Desktop/Clocher/quant/q4_parts/block.23.mlp.gate.weight.scale.fp16",
    "per": "row",
    "rows": 32,
    "cols": 2880,
    "scale_dtype": "fp16",
    "pack": "nibble_lohi",
    "zp": 0,
    "symmetric": true
  },
  {
    "name": "block.3.attn.out.weight",
    "int4_bin": "/home/ricky/Desktop/Clocher/quant/q4_parts/block.3.attn.out.weight.int4",
    "scale_bin": "/home/ricky/Desktop/Clocher/quant/q4_parts/block.3.attn.out.weight.scale.fp16",
    "per": "row",
    "rows": 2880,
    "cols": 4096,
    "scale_dtype": "fp16",
    "pack": "nibble_lohi",
    "zp": 0,
    "symmetric": true
  },
  {
    "name": "block.3.attn.qkv.weight",
    "int4_bin": "/home/ricky/Desktop/Clocher/quant/q4_parts/block.3.attn.qkv.weight.int4",
    "scale_bin": "/home/ricky/Desktop/Clocher/quant/q4_parts/block.3.attn.qkv.weight.scale.fp16",
    "per": "row",
    "rows": 5120,
    "cols": 2880,
    "scale_dtype": "fp16",
    "pack": "nibble_lohi",
    "zp": 0,
    "symmetric": true
  },
  {
    "name": "block.3.mlp.gate.weight",
    "int4_bin": "/home/ricky/Desktop/Clocher/quant/q4_parts/block.3.mlp.gate.weight.int4",
    "scale_bin": "/home/ricky/Desktop/Clocher/quant/q4_parts/block.3.mlp.gate.weight.scale.fp16",
    "per": "row",
    "rows": 32,
    "cols": 2880,
    "scale_dtype": "fp16",
    "pack": "nibble_lohi",
    "zp": 0,
    "symmetric": true
  },
  {
    "name": "block.4.attn.out.weight",
    "int4_bin": "/home/ricky/Desktop/Clocher/quant/q4_parts/block.4.attn.out.weight.int4",
    "scale_bin": "/home/ricky/Desktop/Clocher/quant/q4_parts/block.4.attn.out.weight.scale.fp16",
    "per": "row",
    "rows": 2880,
    "cols": 4096,
    "scale_dtype": "fp16",
    "pack": "nibble_lohi",
    "zp": 0,
    "symmetric": true
  },
  {
    "name": "block.4.attn.qkv.weight",
    "int4_bin": "/home/ricky/Desktop/Clocher/quant/q4_parts/block.4.attn.qkv.weight.int4",
    "scale_bin": "/home/ricky/Desktop/Clocher/quant/q4_parts/block.4.attn.qkv.weight.scale.fp16",
    "per": "row",
    "rows": 5120,
    "cols": 2880,
    "scale_dtype": "fp16",
    "pack": "nibble_lohi",
    "zp": 0,
    "symmetric": true
  },
  {
    "name": "block.4.mlp.gate.weight",
    "int4_bin": "/home/ricky/Desktop/Clocher/quant/q4_parts/block.4.mlp.gate.weight.int4",
    "scale_bin": "/home/ricky/Desktop/Clocher/quant/q4_parts/block.4.mlp.gate.weight.scale.fp16",
    "per": "row",
    "rows": 32,
    "cols": 2880,
    "scale_dtype": "fp16",
    "pack": "nibble_lohi",
    "zp": 0,
    "symmetric": true
  },
  {
    "name": "block.5.attn.out.weight",
    "int4_bin": "/home/ricky/Desktop/Clocher/quant/q4_parts/block.5.attn.out.weight.int4",
    "scale_bin": "/home/ricky/Desktop/Clocher/quant/q4_parts/block.5.attn.out.weight.scale.fp16",
    "per": "row",
    "rows": 2880,
    "cols": 4096,
    "scale_dtype": "fp16",
    "pack": "nibble_lohi",
    "zp": 0,
    "symmetric": true
  },
  {
    "name": "block.5.attn.qkv.weight",
    "int4_bin": "/home/ricky/Desktop/Clocher/quant/q4_parts/block.5.attn.qkv.weight.int4",
    "scale_bin": "/home/ricky/Desktop/Clocher/quant/q4_parts/block.5.attn.qkv.weight.scale.fp16",
    "per": "row",
    "rows": 5120,
    "cols": 2880,
    "scale_dtype": "fp16",
    "pack": "nibble_lohi",
    "zp": 0,
    "symmetric": true
  },
  {
    "name": "block.5.mlp.gate.weight",
    "int4_bin": "/home/ricky/Desktop/Clocher/quant/q4_parts/block.5.mlp.gate.weight.int4",
    "scale_bin": "/home/ricky/Desktop/Clocher/quant/q4_parts/block.5.mlp.gate.weight.scale.fp16",
    "per": "row",
    "rows": 32,
    "cols": 2880,
    "scale_dtype": "fp16",
    "pack": "nibble_lohi",
    "zp": 0,
    "symmetric": true
  },
  {
    "name": "block.6.attn.out.weight",
    "int4_bin": "/home/ricky/Desktop/Clocher/quant/q4_parts/block.6.attn.out.weight.int4",
    "scale_bin": "/home/ricky/Desktop/Clocher/quant/q4_parts/block.6.attn.out.weight.scale.fp16",
    "per": "row",
    "rows": 2880,
    "cols": 4096,
    "scale_dtype": "fp16",
    "pack": "nibble_lohi",
    "zp": 0,
    "symmetric": true
  },
  {
    "name": "block.6.attn.qkv.weight",
    "int4_bin": "/home/ricky/Desktop/Clocher/quant/q4_parts/block.6.attn.qkv.weight.int4",
    "scale_bin": "/home/ricky/Desktop/Clocher/quant/q4_parts/block.6.attn.qkv.weight.scale.fp16",
    "per": "row",
    "rows": 5120,
    "cols": 2880,
    "scale_dtype": "fp16",
    "pack": "nibble_lohi",
    "zp": 0,
    "symmetric": true
  },
  {
    "name": "block.6.mlp.gate.weight",
    "int4_bin": "/home/ricky/Desktop/Clocher/quant/q4_parts/block.6.mlp.gate.weight.int4",
    "scale_bin": "/home/ricky/Desktop/Clocher/quant/q4_parts/block.6.mlp.gate.weight.scale.fp16",
    "per": "row",
    "rows": 32,
    "cols": 2880,
    "scale_dtype": "fp16",
    "pack": "nibble_lohi",
    "zp": 0,
    "symmetric": true
  },
  {
    "name": "block.7.attn.out.weight",
    "int4_bin": "/home/ricky/Desktop/Clocher/quant/q4_parts/block.7.attn.out.weight.int4",
    "scale_bin": "/home/ricky/Desktop/Clocher/quant/q4_parts/block.7.attn.out.weight.scale.fp16",
    "per": "row",
    "rows": 2880,
    "cols": 4096,
    "scale_dtype": "fp16",
    "pack": "nibble_lohi",
    "zp": 0,
    "symmetric": true
  },
  {
    "name": "block.7.attn.qkv.weight",
    "int4_bin": "/home/ricky/Desktop/Clocher/quant/q4_parts/block.7.attn.qkv.weight.int4",
    "scale_bin": "/home/ricky/Desktop/Clocher/quant/q4_parts/block.7.attn.qkv.weight.scale.fp16",
    "per": "row",
    "rows": 5120,
    "cols": 2880,
    "scale_dtype": "fp16",
    "pack": "nibble_lohi",
    "zp": 0,
    "symmetric": true
  },
  {
    "name": "block.7.mlp.gate.weight",
    "int4_bin": "/home/ricky/Desktop/Clocher/quant/q4_parts/block.7.mlp.gate.weight.int4",
    "scale_bin": "/home/ricky/Desktop/Clocher/quant/q4_parts/block.7.mlp.gate.weight.scale.fp16",
    "per": "row",
    "rows": 32,
    "cols": 2880,
    "scale_dtype": "fp16",
    "pack": "nibble_lohi",
    "zp": 0,
    "symmetric": true
  },
  {
    "name": "block.8.attn.out.weight",
    "int4_bin": "/home/ricky/Desktop/Clocher/quant/q4_parts/block.8.attn.out.weight.int4",
    "scale_bin": "/home/ricky/Desktop/Clocher/quant/q4_parts/block.8.attn.out.weight.scale.fp16",
    "per": "row",
    "rows": 2880,
    "cols": 4096,
    "scale_dtype": "fp16",
    "pack": "nibble_lohi",
    "zp": 0,
    "symmetric": true
  },
  {
    "name": "block.8.attn.qkv.weight",
    "int4_bin": "/home/ricky/Desktop/Clocher/quant/q4_parts/block.8.attn.qkv.weight.int4",
    "scale_bin": "/home/ricky/Desktop/Clocher/quant/q4_parts/block.8.attn.qkv.weight.scale.fp16",
    "per": "row",
    "rows": 5120,
    "cols": 2880,
    "scale_dtype": "fp16",
    "pack": "nibble_lohi",
    "zp": 0,
    "symmetric": true
  },
  {
    "name": "block.8.mlp.gate.weight",
    "int4_bin": "/home/ricky/Desktop/Clocher/quant/q4_parts/block.8.mlp.gate.weight.int4",
    "scale_bin": "/home/ricky/Desktop/Clocher/quant/q4_parts/block.8.mlp.gate.weight.scale.fp16",
    "per": "row",
    "rows": 32,
    "cols": 2880,
    "scale_dtype": "fp16",
    "pack": "nibble_lohi",
    "zp": 0,
    "symmetric": true
  },
  {
    "name": "block.9.attn.out.weight",
    "int4_bin": "/home/ricky/Desktop/Clocher/quant/q4_parts/block.9.attn.out.weight.int4",
    "scale_bin": "/home/ricky/Desktop/Clocher/quant/q4_parts/block.9.attn.out.weight.scale.fp16",
    "per": "row",
    "rows": 2880,
    "cols": 4096,
    "scale_dtype": "fp16",
    "pack": "nibble_lohi",
    "zp": 0,
    "symmetric": true
  },
  {
    "name": "block.9.attn.qkv.weight",
    "int4_bin": "/home/ricky/Desktop/Clocher/quant/q4_parts/block.9.attn.qkv.weight.int4",
    "scale_bin": "/home/ricky/Desktop/Clocher/quant/q4_parts/block.9.attn.qkv.weight.scale.fp16",
    "per": "row",
    "rows": 5120,
    "cols": 2880,
    "scale_dtype": "fp16",
    "pack": "nibble_lohi",
    "zp": 0,
    "symmetric": true
  },
  {
    "name": "block.9.mlp.gate.weight",
    "int4_bin": "/home/ricky/Desktop/Clocher/quant/q4_parts/block.9.mlp.gate.weight.int4",
    "scale_bin": "/home/ricky/Desktop/Clocher/quant/q4_parts/block.9.mlp.gate.weight.scale.fp16",
    "per": "row",
    "rows": 32,
    "cols": 2880,
    "scale_dtype": "fp16",
    "pack": "nibble_lohi",
    "zp": 0,
    "symmetric": true
  }
]